PyRubik/GetScramble.py
PyRubik/Scramble.py
PyRubik/Tools.py
PyRubik/__init__.py
pyrubik-0.1.0.2.dist-info/licenses/LICENSE
tests/GetScramble_test.py
tests/Testing.py
tests/__init__.py
tests/install_test.py
pyrubik-0.1.0.2.dist-info/METADATA
pyrubik-0.1.0.2.dist-info/WHEEL
pyrubik-0.1.0.2.dist-info/top_level.txt
pyrubik-0.1.0.2.dist-info/RECORD
