Metadata-Version: 2.4
Name: PyRubik
Version: 0.1.0.2
Summary: A Python module to make speedcubing projects a piece of cake.
Home-page: https://github.com/Samuel-de-Oliveira/PyCubing/
Author: Samuel de Oliveira
Author-email: samwolfg12@gmail.com
License: MIT
Keywords: cubing rubik rubik's cube solver scramble cube pyrubik
Classifier: License :: OSI Approved :: MIT License
Classifier: Operating System :: OS Independent
Classifier: Programming Language :: Python :: 3
Classifier: Topic :: Software Development :: Libraries :: Python Modules
Classifier: Topic :: Education
Classifier: Topic :: Games/Entertainment
Requires-Python: >=3.10
License-File: LICENSE
Dynamic: author
Dynamic: author-email
Dynamic: classifier
Dynamic: description
Dynamic: description-content-type
Dynamic: home-page
Dynamic: keywords
Dynamic: license
Dynamic: license-file
Dynamic: requires-python
Dynamic: summary
